security/__init__.py
security/admin.py
security/auth.py
security/auth_throttling/__init__.py
security/auth_throttling/views.py
security/forms.py
security/middleware.py
security/migrations/0001_initial.py
security/migrations/0002_convert_pass_expiry_user_to_one2one.py
security/migrations/__init__.py
security/models.py
security/password_expiry.py
security/urls.py
security/views.py
django_security-1.1.5.dist-info/METADATA
django_security-1.1.5.dist-info/WHEEL
django_security-1.1.5.dist-info/licenses/LICENSE.md
django_security-1.1.5.dist-info/RECORD
