Metadata-Version: 2.4
Name: django-security
Version: 1.1.5
Summary: Models, views, middlewares and forms to facilitate security hardening of Django applications.
License: BSD-3-Clause
License-File: LICENSE.md
Author: Security Compass
Author-email: contact@securitycompass.com
Requires-Python: >=3.12,<3.13
Classifier: Development Status :: 5 - Production/Stable
Classifier: Framework :: Django
Classifier: Intended Audience :: Developers
Classifier: License :: OSI Approved :: BSD License
Classifier: Natural Language :: English
Classifier: Operating System :: OS Independent
Classifier: Programming Language :: Python :: 3
Classifier: Programming Language :: Python :: 3.12
Classifier: Topic :: Software Development :: Libraries :: Python Modules
Requires-Dist: django (>=4.2,<4.3)
Requires-Dist: python-dateutil (==2.9.0.post0)
Requires-Dist: south (==1.0.2)
Requires-Dist: ua_parser (==0.18.0)
Project-URL: Homepage, https://github.com/sdelements/django-security
